test/__init__.py
websiteclassificationapi/__init__.py
websiteclassificationapi-2.10.dist-info/LICENSE
websiteclassificationapi-2.10.dist-info/METADATA
websiteclassificationapi-2.10.dist-info/WHEEL
websiteclassificationapi-2.10.dist-info/top_level.txt
websiteclassificationapi-2.10.dist-info/RECORD
