Metadata-Version: 2.1
Name: websiteclassificationapi
Version: 2.10
Summary: Website classification API
Home-page: https://github.com/websitecategorization/websiteclassificationnapi
Author-email: info@websitecategorizationapi.com
License: UNKNOWN
Keywords: website categorization,classification,categorization
Platform: UNKNOWN
Classifier: License :: OSI Approved :: MIT License
Classifier: Environment :: GPU :: NVIDIA CUDA :: 11.3
Classifier: Environment :: GPU :: NVIDIA CUDA :: 11.0
Classifier: Environment :: GPU :: NVIDIA CUDA
Classifier: Environment :: GPU :: NVIDIA CUDA :: 11.2
Classifier: Environment :: GPU :: NVIDIA CUDA :: 10.1
Classifier: Programming Language :: Python :: 3 :: Only
